jepy/__init__.py
jepy/jepy.py
jepy/jepy_exceptions.py
Jepy-1.0.0.dist-info/LICENSE
Jepy-1.0.0.dist-info/METADATA
Jepy-1.0.0.dist-info/WHEEL
Jepy-1.0.0.dist-info/top_level.txt
Jepy-1.0.0.dist-info/RECORD
