Metadata-Version: 2.1
Name: Jepy
Version: 1.0.0
Summary: A simple Python wrapper to access the Johns Eastern Company API.
Home-page: https://github.com/JECO/jepy
Author: JECO
Author-email: support@je.zendesk.com
License: UNKNOWN
Platform: UNKNOWN
Classifier: Development Status :: 5 - Production/Stable
Classifier: License :: OSI Approved :: GNU General Public License v3 (GPLv3)
Classifier: Programming Language :: Python :: 3.7
Classifier: Operating System :: OS Independent
Requires-Python: >=3.4
License-File: LICENSE
Requires-Dist: quick-rest (>=0.1.7)
Requires-Dist: dicttoxml (>=1.7.4)
